LICENSE
MANIFEST.in
README.md
VERSION
pyproject.toml
requirements.txt
setup.py
cova.egg-info/PKG-INFO
cova.egg-info/SOURCES.txt
cova.egg-info/dependency_links.txt
cova.egg-info/entry_points.txt
cova.egg-info/not-zip-safe
cova.egg-info/requires.txt
cova.egg-info/top_level.txt
covalent/__init__.py
covalent/_data_store/__init__.py
covalent/_data_store/datastore.py
covalent/_data_store/models.py
covalent/_data_store/storage_backends/__init__.py
covalent/_data_store/storage_backends/localstoragebackend.py
covalent/_data_store/storage_backends/storagebackend.py
covalent/_dispatcher_plugins/__init__.py
covalent/_dispatcher_plugins/base.py
covalent/_dispatcher_plugins/local.py
covalent/_file_transfer/__init__.py
covalent/_file_transfer/enums.py
covalent/_file_transfer/file.py
covalent/_file_transfer/file_transfer.py
covalent/_file_transfer/folder.py
covalent/_file_transfer/strategies/__init__.py
covalent/_file_transfer/strategies/http_strategy.py
covalent/_file_transfer/strategies/rsync_strategy.py
covalent/_file_transfer/strategies/s3_strategy.py
covalent/_file_transfer/strategies/transfer_strategy_base.py
covalent/_results_manager/__init__.py
covalent/_results_manager/result.py
covalent/_results_manager/results_manager.py
covalent/_results_manager/utils.py
covalent/_results_manager/wait.py
covalent/_results_manager/write_result_to_db.py
covalent/_shared_files/__init__.py
covalent/_shared_files/config.py
covalent/_shared_files/context_managers.py
covalent/_shared_files/defaults.py
covalent/_shared_files/logger.py
covalent/_shared_files/util_classes.py
covalent/_shared_files/utils.py
covalent/_workflow/__init__.py
covalent/_workflow/deps.py
covalent/_workflow/depsbash.py
covalent/_workflow/depscall.py
covalent/_workflow/depspip.py
covalent/_workflow/electron.py
covalent/_workflow/lattice.py
covalent/_workflow/lepton.py
covalent/_workflow/transport.py
covalent/executor/__init__.py
covalent/executor/base.py
covalent/executor/executor_plugins/dask.py
covalent/executor/executor_plugins/local.py
covalent/leptons/__init__.py
covalent/utils/__init__.py
covalent/utils/migrate.py
covalent_dispatcher/__init__.py
covalent_dispatcher/entry_point.py
