Metadata-Version: 2.1
Name: cova
Version: 0.177.0
Summary: Covalent Workflow Tool
Home-page: https://github.com/AgnostiqHQ/covalent
Download-URL: https://github.com/AgnostiqHQ/covalent/archive/v0.177.0.tar.gz
Author: Agnostiq
Author-email: support@agnostiq.ai
Maintainer: Agnostiq
License: GNU Affero GPL v3.0
Platform: UNKNOWN
Classifier: Development Status :: 4 - Beta
Classifier: Environment :: Console
Classifier: Intended Audience :: Developers
Classifier: Intended Audience :: Education
Classifier: Intended Audience :: Science/Research
Classifier: License :: OSI Approved :: GNU Affero General Public License v3
Classifier: Natural Language :: English
Classifier: Operating System :: MacOS :: MacOS X
Classifier: Operating System :: POSIX
Classifier: Programming Language :: Python :: 3
Classifier: Programming Language :: Python :: 3 :: Only
Classifier: Programming Language :: Python :: 3.8
Classifier: Programming Language :: Python :: 3.9
Classifier: Programming Language :: Python :: 3.10
Classifier: Topic :: Adaptive Technologies
Classifier: Topic :: Scientific/Engineering
Classifier: Topic :: Scientific/Engineering :: Interface Engine/Protocol Translator
Classifier: Topic :: Software Development
Classifier: Topic :: System :: Distributed Computing
Provides-Extra: aws
License-File: LICENSE
